dataguillm/__init__.py
dataguillm/dataguillm.py
tests/__init__.py
tests/test_eda.py
dataguillm-1.2.dist-info/LICENSE.txt
dataguillm-1.2.dist-info/METADATA
dataguillm-1.2.dist-info/WHEEL
dataguillm-1.2.dist-info/top_level.txt
dataguillm-1.2.dist-info/RECORD
