Metadata-Version: 2.1
Name: dataguillm
Version: 1.2
Summary: A package for Exploratory Data Analysis (EDA)
Author: Sagnik Banerjee
Author-email: sagu7065@gmail.com
License: MIT
Classifier: Programming Language :: Python :: 3
Classifier: License :: OSI Approved :: MIT License
Classifier: Operating System :: OS Independent
Requires-Python: >=3.10
License-File: LICENSE.txt
Requires-Dist: pandas
Requires-Dist: numpy
Requires-Dist: seaborn
Requires-Dist: plotly
Requires-Dist: scipy
Requires-Dist: statsmodels
Requires-Dist: datapane
Requires-Dist: scikit-learn
Requires-Dist: groq
Requires-Dist: python-docx
